lockfile_parser/__init__.py
lockfile_parser/cargo_parser.py
lockfile_parser/poetry_parser.py
lockfile_parser-0.2.0.dist-info/METADATA
lockfile_parser-0.2.0.dist-info/WHEEL
lockfile_parser-0.2.0.dist-info/top_level.txt
lockfile_parser-0.2.0.dist-info/RECORD
