Metadata-Version: 2.1
Name: lockfile-parser
Version: 0.2.0
Summary: A mininal lockfile parser in python
Home-page: https://github.com/nikhilmitrax/lockfile-parser-py
Author: Nikhil
Author-email: nm2868@columbia.edu
License: UNKNOWN
Platform: UNKNOWN
Classifier: Programming Language :: Python :: 3
Classifier: License :: OSI Approved :: MIT License
Classifier: Operating System :: OS Independent
Requires-Python: >=3.6
Requires-Dist: toml >=0.10.2
